torchode/__init__.py
torchode/adjoints.py
torchode/interface.py
torchode/interpolation.py
torchode/problems.py
torchode/solution.py
torchode/status_codes.py
torchode/step_size_controllers.py
torchode/terms.py
torchode/typing.py
torchode/single_step_methods/__init__.py
torchode/single_step_methods/base.py
torchode/single_step_methods/dopri5.py
torchode/single_step_methods/euler.py
torchode/single_step_methods/heun.py
torchode/single_step_methods/runge_kutta.py
torchode/single_step_methods/tsit5.py
torchode-1.0.0.dist-info/LICENSE
torchode-1.0.0.dist-info/WHEEL
torchode-1.0.0.dist-info/METADATA
torchode-1.0.0.dist-info/RECORD
