Metadata-Version: 2.1
Name: torchode
Version: 1.0.0
Summary: A parallel ODE solver for PyTorch
Author-email: Marten Lienen <m.lienen@tum.de>
Requires-Python: >= 3.8
Classifier: Development Status :: 5 - Production/Stable
Classifier: Intended Audience :: Developers
Classifier: Intended Audience :: Science/Research
Classifier: License :: OSI Approved :: MIT License
Classifier: Operating System :: OS Independent
Classifier: Programming Language :: Python
Requires-Dist: sympy ~= 1.10
Requires-Dist: torch >= 2.0
Requires-Dist: torchtyping ~= 0.1.4
Requires-Dist: pytest-benchmark ; extra == "benchmark"
Requires-Dist: pytest ; extra == "test"
Requires-Dist: numpy ~= 1.22 ; extra == "test"
Project-URL: homepage, https://github.com/martenlienen/torchode
Provides-Extra: benchmark
Provides-Extra: test
